gmailer/__init__.py
gmailer/admin.py
gmailer/apps.py
gmailer/gmail.py
gmailer/models.py
gmailer/tests.py
gmailer/urls.py
gmailer/views.py
gmailer/data/sample.json
gmailer/migrations/__init__.py
django_google_mailer-0.3.1.dist-info/LICENSE
django_google_mailer-0.3.1.dist-info/METADATA
django_google_mailer-0.3.1.dist-info/WHEEL
django_google_mailer-0.3.1.dist-info/top_level.txt
django_google_mailer-0.3.1.dist-info/RECORD
