Metadata-Version: 2.1
Name: django-google-mailer
Version: 0.3.1
Summary: Django Package which enable Gmail API to send email inside your project
Home-page: https://github.com/nikhiljohn10/django-google-mailer
Author: Nikhil John
Author-email: me@nikz.in
License: MIT
Project-URL: Documentation, https://django-google-mailer.readthedocs.io/
Project-URL: Changelog, https://django-google-mailer.readthedocs.io/en/latest/change.html
Keywords: Django,Package,Gmail,API,email,OAuth,Google
Platform: any
Classifier: Development Status :: 5 - Production/Stable
Classifier: Environment :: Web Environment
Classifier: Framework :: Django
Classifier: Framework :: Django :: 3.0
Classifier: Framework :: Django :: 3.1
Classifier: Intended Audience :: Developers
Classifier: License :: OSI Approved :: MIT License
Classifier: Operating System :: OS Independent
Classifier: Programming Language :: Python
Classifier: Programming Language :: Python :: 3
Classifier: Programming Language :: Python :: 3 :: Only
Classifier: Programming Language :: Python :: 3.6
Classifier: Programming Language :: Python :: 3.7
Classifier: Programming Language :: Python :: 3.8
Classifier: Programming Language :: Python :: 3.9
Classifier: Topic :: Internet :: WWW/HTTP
Classifier: Topic :: Internet :: WWW/HTTP :: Dynamic Content
Classifier: Topic :: Software Development :: Libraries :: Application Frameworks
Classifier: Topic :: Software Development :: Libraries :: Python Modules
Requires-Python: >=3.6
Requires-Dist: Django (>=3.1.3)
Requires-Dist: google-api-python-client (>=1.12.5)
Requires-Dist: google-auth-oauthlib (>=0.4.2)
